nendo_plugin_vampnet/__init__.py
nendo_plugin_vampnet/config.py
nendo_plugin_vampnet/nendo_vampnet.py
nendo_plugin_vampnet/plugin.py
nendo_plugin_vampnet-0.1.3.dist-info/LICENSE
nendo_plugin_vampnet-0.1.3.dist-info/METADATA
nendo_plugin_vampnet-0.1.3.dist-info/WHEEL
nendo_plugin_vampnet-0.1.3.dist-info/RECORD
